met/__init__.py
met/location.py
met/metportal.py
met/metvariable.py
met/observations.py
met/package_info.py
met/wave.py
met/wind.py
met/blueprints/__init__.py
met/blueprints/location.py
met/blueprints/metportal.py
met/blueprints/metvariable.py
met/blueprints/observations.py
met/blueprints/wave.py
met/blueprints/wind.py
met/jobs/__init__.py
met/jobs/job.py
met/jobs/jobresult.py
met/jobs/jobrunner.py
met/jobs/blueprints/__init__.py
met/jobs/blueprints/job.py
met/jobs/blueprints/jobresult.py
met/jobs/blueprints/jobrunner.py
met/nora3/__init__.py
met/nora3/field.py
met/nora3/fieldpoint.py
met/nora3/windarea.py
met/nora3/blueprints/__init__.py
met/nora3/blueprints/field.py
met/nora3/blueprints/fieldpoint.py
met/nora3/blueprints/windarea.py
met/scatter/__init__.py
met/scatter/scatter.py
met/scatter/sector.py
met/scatter/wave.py
met/scatter/windcurrent.py
met/scatter/blueprints/__init__.py
met/scatter/blueprints/scatter.py
met/scatter/blueprints/sector.py
met/scatter/blueprints/wave.py
met/scatter/blueprints/windcurrent.py
metlib/__init__.py
metlib/catalog.py
metlib/create_location_entities.py
metlib/jsonencoder.py
metlib/latlon.py
metlib/scatter.py
metlib/normet/__init__.py
metlib/normet/cache.py
metlib/normet/level_values.py
metlib/normet/subset.py
metlib/normet/values.py
metlib/normet/nora3/__init__.py
metlib/normet/nora3/download_wind.py
metlib/normet/nora3/read_waves.py
metlib/normet/nora3/read_winds.py
metlib/normet/norkyst/__init__.py
metlib/normet/norkyst/read_currents.py
metocean/__init__.py
metocean/metocean.py
metocean/package_info.py
metocean/blueprints/__init__.py
metocean/blueprints/metocean.py
metocean/hindcast/__init__.py
metocean/hindcast/hindcast.py
metocean/hindcast/stochasticcurrent.py
metocean/hindcast/stochasticwave.py
metocean/hindcast/stochasticwind.py
metocean/hindcast/blueprints/__init__.py
metocean/hindcast/blueprints/hindcast.py
metocean/hindcast/blueprints/stochasticcurrent.py
metocean/hindcast/blueprints/stochasticwave.py
sfibluesmetlib-0.1.0.dev1.dist-info/METADATA
sfibluesmetlib-0.1.0.dev1.dist-info/WHEEL
sfibluesmetlib-0.1.0.dev1.dist-info/top_level.txt
sfibluesmetlib-0.1.0.dev1.dist-info/RECORD
